team_query/__init__.py
team_query/builders/__init__.py
team_query/builders/compilers/__init__.py
team_query/builders/compilers/base.py
team_query/builders/compilers/js/__init__.py
team_query/builders/compilers/js/compiler.py
team_query/builders/compilers/js/templates.py
team_query/builders/compilers/python/__init__.py
team_query/builders/compilers/python/compiler.py
team_query/builders/compilers/python/templates.py
team_query/builders/javascript_builder.py
team_query/builders/python_builder.py
team_query/cli.py
team_query/config.py
team_query/models.py
team_query/parser.py
team_query/sql_parser.py
team_query-1.0.19.dist-info/LICENSE
team_query-1.0.19.dist-info/METADATA
team_query-1.0.19.dist-info/WHEEL
team_query-1.0.19.dist-info/entry_points.txt
team_query-1.0.19.dist-info/RECORD
