Metadata-Version: 2.3
Name: team-query
Version: 1.0.19
Summary: The ORM you get when you love SQL but hate typing it twice.
License: MIT
Keywords: sql,orm,database,code-generator,postgresql
Author: Javier Echenique
Author-email: akerbeltz@gmail.com
Requires-Python: >=3.9,<4.0
Classifier: Development Status :: 4 - Beta
Classifier: Environment :: Console
Classifier: Intended Audience :: Developers
Classifier: License :: OSI Approved :: MIT License
Classifier: Programming Language :: Python :: 3
Classifier: Programming Language :: Python :: 3.9
Classifier: Programming Language :: Python :: 3.10
Classifier: Programming Language :: Python :: 3.11
Classifier: Programming Language :: Python :: 3.12
Classifier: Programming Language :: Python :: 3.13
Classifier: Programming Language :: Python :: 3.8
Classifier: Topic :: Database
Classifier: Topic :: Software Development :: Code Generators
Requires-Dist: click (>=8.1.3,<9.0.0)
Requires-Dist: docutils (==0.21.2)
Requires-Dist: importlib-metadata (>=6.0.0,<7.0.0)
Requires-Dist: pyyaml (>=6.0,<7.0)
Project-URL: Documentation, https://github.com/jechenique/team-query#readme
Project-URL: Homepage, https://github.com/jechenique/team-query
Project-URL: Repository, https://github.com/jechenique/team-query
